imagedl/__init__.py
imagedl/imagedl.py
imagedl/modules/__init__.py
imagedl/modules/sources/__init__.py
imagedl/modules/sources/baidu.py
imagedl/modules/sources/base.py
imagedl/modules/sources/bing.py
imagedl/modules/sources/danbooru.py
imagedl/modules/sources/duckduckgo.py
imagedl/modules/sources/gelbooru.py
imagedl/modules/sources/google.py
imagedl/modules/sources/i360.py
imagedl/modules/sources/pixabay.py
imagedl/modules/sources/safebooru.py
imagedl/modules/sources/sogou.py
imagedl/modules/sources/unsplash.py
imagedl/modules/sources/yahoo.py
imagedl/modules/sources/yandex.py
imagedl/modules/utils/__init__.py
imagedl/modules/utils/io.py
imagedl/modules/utils/logger.py
imagedl/modules/utils/misc.py
imagedl/modules/utils/modulebuilder.py
pyimagedl-0.3.0.dist-info/LICENSE
pyimagedl-0.3.0.dist-info/METADATA
pyimagedl-0.3.0.dist-info/WHEEL
pyimagedl-0.3.0.dist-info/entry_points.txt
pyimagedl-0.3.0.dist-info/top_level.txt
pyimagedl-0.3.0.dist-info/zip-safe
pyimagedl-0.3.0.dist-info/RECORD
