Metadata-Version: 2.1
Name: pyimagedl
Version: 0.3.0
Summary: Imagedl: Search and download images from specific websites
Home-page: https://github.com/CharlesPikachu/imagedl
Author: Zhenchao Jin
Author-email: charlesblwx@gmail.com
License: Apache License 2.0
Classifier: License :: OSI Approved :: Apache Software License
Classifier: Programming Language :: Python :: 3
Classifier: Intended Audience :: Developers
Classifier: Operating System :: OS Independent
License-File: LICENSE
Requires-Dist: requests
Requires-Dist: alive-progress
Requires-Dist: pyfreeproxy
Requires-Dist: fake-useragent
Requires-Dist: beautifulsoup4
Requires-Dist: lxml
Requires-Dist: click
Requires-Dist: json-repair
Requires-Dist: prettytable
Requires-Dist: platformdirs
Requires-Dist: pathvalidate
Requires-Dist: standard-imghdr
